[{"line":2,"elements":[{"start_timestamp":"2025-01-02T00:46:53.701Z","line":11,"name":"validate the form checkbox functionality","description":"","id":"checkbox-functionality;validate-the-form-checkbox-functionality;;2","type":"scenario","keyword":"Scenario Outline","steps":[{"result":{"duration":4902605800,"status":"passed"},"line":5,"name":"I navigate to test checkbox https://opensource-demo.orangehrmlive.com/web/index.php/auth/login","match":{"arguments":[{"val":"https://opensource-demo.orangehrmlive.com/web/index.php/auth/login","offset":28}],"location":"app.seleniumautomation.stepdefinitions.Checkboxsteps.i_navigate_to_test_checkbox_url(java.lang.String)"},"keyword":"Given "},{"result":{"status":"undefined"},"line":6,"name":"I checked that checkbox is selected and validate the message","match":{},"keyword":"When "},{"result":{"status":"skipped"},"line":7,"name":"checkbox is not selected validate the message","match":{},"keyword":"Then "}],"tags":[{"name":"@checkbox"},{"name":"@all"}]}],"name":"Checkbox functionality","description":"","id":"checkbox-functionality","keyword":"Feature","uri":"file:src/test/resources/features/Checkbox.feature","tags":[{"name":"@checkbox","type":"Tag","location":{"line":1,"column":1}},{"name":"@all","type":"Tag","location":{"line":1,"column":11}}]},{"line":3,"elements":[{"start_timestamp":"2025-01-02T00:46:58.627Z","line":17,"name":"validate the form dropdown functionality","description":"","id":"dropdown-functionality;validate-the-form-dropdown-functionality;;2","type":"scenario","keyword":"Scenario Outline","steps":[{"result":{"duration":5119938800,"status":"passed"},"line":8,"name":"I navigate to only testing https://only-testing-blog.blogspot.com/2013/09/test.html","match":{"arguments":[{"val":"https://only-testing-blog.blogspot.com/2013/09/test.html","offset":27}],"location":"app.seleniumautomation.stepdefinitions.Dropdownsteps.i_navigate_to_only_testing_url(java.lang.String)"},"keyword":"Given "},{"result":{"duration":5190042100,"status":"passed"},"line":9,"name":"I select a Singapore from the dropdown","match":{"arguments":[{"val":"Singapore","offset":11}],"location":"app.seleniumautomation.stepdefinitions.Dropdownsteps.i_select_a_vale_from_the_dropdown(java.lang.String)"},"keyword":"When "},{"result":{"duration":48589700,"status":"passed"},"line":10,"name":"I validate if the selected value is populated","match":{"location":"app.seleniumautomation.stepdefinitions.Dropdownsteps.validate_if_the_selected_value_is_populated()"},"keyword":"Then "}],"tags":[{"name":"@Dropdown"},{"name":"@all"}]}],"name":"Dropdown functionality","description":"","id":"dropdown-functionality","keyword":"Feature","uri":"file:src/test/resources/features/Dropdown.feature","tags":[{"name":"@Dropdown","type":"Tag","location":{"line":2,"column":1}},{"name":"@all","type":"Tag","location":{"line":2,"column":11}}]},{"line":2,"elements":[{"start_timestamp":"2025-01-02T00:47:08.997Z","line":11,"name":"validate the form authentication functionality","description":"","id":"form-authentication-functionality;validate-the-form-authentication-functionality;;2","type":"scenario","keyword":"Scenario Outline","steps":[{"result":{"duration":5148274900,"status":"passed"},"line":5,"name":"I navigate to the https://the-internet.herokuapp.com/","match":{"arguments":[{"val":"https://the-internet.herokuapp.com/","offset":18}],"location":"app.seleniumautomation.stepdefinitions.FormAuthenticationSteps.i_navigate_to_the_url(java.lang.String)"},"keyword":"Given "},{"result":{"duration":2135227300,"status":"passed"},"line":6,"name":"I click on form authentication and enter tomsmith and SuperSecretPassword!","match":{"arguments":[{"val":"tomsmith","offset":41},{"val":"SuperSecretPassword!","offset":54}],"location":"app.seleniumautomation.stepdefinitions.FormAuthenticationSteps.i_click_on_form_authentication_and_enter_credentials(java.lang.String,java.lang.String)"},"keyword":"When "},{"result":{"duration":32633600,"status":"passed"},"line":7,"name":"validate login successful","match":{"location":"app.seleniumautomation.stepdefinitions.FormAuthenticationSteps.validate_login_successful()"},"keyword":"Then "}],"tags":[{"name":"@formauthentication"},{"name":"@all"}]}],"name":"Form Authentication functionality","description":"","id":"form-authentication-functionality","keyword":"Feature","uri":"file:src/test/resources/features/FormAuthentication.feature","tags":[{"name":"@formauthentication","type":"Tag","location":{"line":1,"column":1}},{"name":"@all","type":"Tag","location":{"line":1,"column":21}}]}]